vfc_services/VFCMicroService.py
vfc_services/__init__.py
vfc_services-0.1.0.dist-info/METADATA
vfc_services-0.1.0.dist-info/WHEEL
vfc_services-0.1.0.dist-info/top_level.txt
vfc_services-0.1.0.dist-info/RECORD
